sinaps/__init__.py
sinaps/core/__init__.py
sinaps/core/channels.py
sinaps/core/model.py
sinaps/core/simulation.py
sinaps/core/species.py
sinaps/data/__init__.py
sinaps/data/data.py
sinaps/data/io.py
sinaps/gui/__init__.py
sinaps/gui/graph.py
sinaps/gui/neuron.py
SiNAPS-0.3.1.dist-info/LICENSE
SiNAPS-0.3.1.dist-info/METADATA
SiNAPS-0.3.1.dist-info/WHEEL
SiNAPS-0.3.1.dist-info/top_level.txt
SiNAPS-0.3.1.dist-info/RECORD
