Metadata-Version: 2.1
Name: SiNAPS
Version: 0.3.1
Summary: Neuronal simulation package
Author: Claire Guerrier
Author-email: claire.guerrier@univ-cotedazur.fr
License: UNKNOWN
Platform: UNKNOWN
Requires-Python: >=3.6
License-File: LICENSE
Requires-Dist: numpy
Requires-Dist: param (==1.10.0)
Requires-Dist: pandas
Requires-Dist: quantiphy
Requires-Dist: scipy (>=1.0.0)
Requires-Dist: hvplot
Requires-Dist: networkx
Requires-Dist: datashader
Requires-Dist: tqdm
Requires-Dist: numba (>=0.55)
